setup.py
asyncio_mongo/__init__.py
asyncio_mongo/auth.py
asyncio_mongo/collection.py
asyncio_mongo/connection.py
asyncio_mongo/database.py
asyncio_mongo/exceptions.py
asyncio_mongo/filter.py
asyncio_mongo/log.py
asyncio_mongo/pool.py
asyncio_mongo/protocol.py
asyncio_mongo.egg-info/PKG-INFO
asyncio_mongo.egg-info/SOURCES.txt
asyncio_mongo.egg-info/dependency_links.txt
asyncio_mongo.egg-info/requires.txt
asyncio_mongo.egg-info/top_level.txt
asyncio_mongo/_bson/__init__.py
asyncio_mongo/_bson/_cbsonmodule.c
asyncio_mongo/_bson/binary.py
asyncio_mongo/_bson/buffer.c
asyncio_mongo/_bson/code.py
asyncio_mongo/_bson/dbref.py
asyncio_mongo/_bson/encoding_helpers.c
asyncio_mongo/_bson/errors.py
asyncio_mongo/_bson/json_util.py
asyncio_mongo/_bson/max_key.py
asyncio_mongo/_bson/min_key.py
asyncio_mongo/_bson/objectid.py
asyncio_mongo/_bson/py3compat.py
asyncio_mongo/_bson/son.py
asyncio_mongo/_bson/time64.c
asyncio_mongo/_bson/timestamp.py
asyncio_mongo/_bson/tz_util.py
asyncio_mongo/_pymongo/__init__.py
asyncio_mongo/_pymongo/_cmessagemodule.c
asyncio_mongo/_pymongo/auth.py
asyncio_mongo/_pymongo/collection.py
asyncio_mongo/_pymongo/common.py
asyncio_mongo/_pymongo/connection.py
asyncio_mongo/_pymongo/cursor.py
asyncio_mongo/_pymongo/cursor_manager.py
asyncio_mongo/_pymongo/database.py
asyncio_mongo/_pymongo/errors.py
asyncio_mongo/_pymongo/helpers.py
asyncio_mongo/_pymongo/master_slave_connection.py
asyncio_mongo/_pymongo/message.py
asyncio_mongo/_pymongo/mongo_client.py
asyncio_mongo/_pymongo/mongo_replica_set_client.py
asyncio_mongo/_pymongo/pool.py
asyncio_mongo/_pymongo/read_preferences.py
asyncio_mongo/_pymongo/replica_set_connection.py
asyncio_mongo/_pymongo/son_manipulator.py
asyncio_mongo/_pymongo/ssl_match_hostname.py
asyncio_mongo/_pymongo/thread_util.py
asyncio_mongo/_pymongo/uri_parser.py