Metadata-Version: 1.1
Name: asyncio-mongo
Version: 0.2.4
Summary: Asynchronous Python 3.3+ driver for MongoDB <http://www.mongodb.org>
Home-page: https://bitbucket.org/mrdon/asyncio-mongo
Author: Alexandre Fiori, Don Brown
Author-email: mrdon@twdata.org
License: Apache License, Version 2.0
Keywords: mongo,mongodb,pymongo,gridfs,asyncio_mongo,asyncio
Platform: UNKNOWN
Classifier: Development Status :: 2 - Pre-Alpha
Classifier: Intended Audience :: Developers
Classifier: License :: OSI Approved :: Apache Software License
Classifier: Operating System :: MacOS :: MacOS X
Classifier: Operating System :: Microsoft :: Windows
Classifier: Operating System :: POSIX
Classifier: Programming Language :: Python
Classifier: Topic :: Database
